xontrib_conda_project/__init__.py
xontrib_conda_project/conda_project.xsh
xontrib_conda_project-0.1.0.dist-info/LICENSE
xontrib_conda_project-0.1.0.dist-info/WHEEL
xontrib_conda_project-0.1.0.dist-info/METADATA
xontrib_conda_project-0.1.0.dist-info/RECORD
