Metadata-Version: 2.1
Name: xontrib-conda-project
Version: 0.1.0
Summary: Automatically activate conda environments when switching projects
License: MIT
Author: Dominic Ward
Author-email: dom@deeuu.me
Requires-Python: >=3.7,<4.0
Classifier: License :: OSI Approved :: MIT License
Classifier: Programming Language :: Python :: 3
Classifier: Programming Language :: Python :: 3.7
Classifier: Programming Language :: Python :: 3.8
Requires-Dist: xonsh
